ram.v
module RAM (clk, read_address, write_address, write, din, dout);
    parameter data_width = 8; 
    parameter addr_width = 8;
    //parameter filename = "sw_led.txt";

    input clk, write;
    input [addr_width-1:0] read_address, write_address;
    input [data_width-1:0] din;
    output [data_width-1:0] dout;
    reg [data_width-1:0] dout;

    reg [data_width-1:0] mem [2**addr_width-1:0];

    always @ (posedge clk) begin
        if (write) 
            mem[write_address] <= din;
        dout <= mem[read_address];
    end
endmodule

regfile.v
module reg_load_enable(clk, in, enable, out);
    parameter k = 16;
    input clk, enable;
    input [k-1:0] in;
    output [k-1:0] out;
    wire [k-1:0] mux_into_reg;

    DFF_Alex #(k) DFF0 (clk, mux_into_reg, out);
    multiplexer_2input #(k) MUX0 (in, out, enable, mux_into_reg);
endmodule

module multiplexer_2input(a1, a0, s, out); // this multiplexer is to be used ONLY with the enable-registers
    parameter k = 1;
    input [k-1:0] a1, a0;
    input s; // select signal s needs to be only 1 bit, if HIGH then write in value to register, if LOW then maintain the current value
    output reg [k-1:0] out;

    always @(*) begin
        case(s)
            1'b0: out = a0;
            1'b1: out = a1;
            default: out = {k{1'bx}};
        endcase
    end
endmodule

module DFF_Alex(clk, in, out);
    parameter n = 1;
    input clk;
    input [n-1:0] in;
    output reg [n-1:0] out;

    always @(posedge clk)
        out = in; 
endmodule

rpn.v
`include "regfile.v"
`include "ram.v"

// Seven segment display definitions 
`define ZERO  		7'b1000000
`define ONE   		7'b1111001
`define TWO   		7'b0100100
`define THREE 		7'b0110000
`define FOUR  		7'b0011001
`define FIVE  		7'b0010010
`define SIX   		7'b0000010
`define SEVEN 		7'b1111000
`define EIGHT 		7'b0000000
`define NINE  		7'b0011000
`define E     		7'b0000110
`define r     		7'b0101111
`define o     		7'b0100011
`define OFF   		7'b1111111

// State machine definitions
`define S_WAIT		4'b0000
`define S_WRITE1	4'b0001
`define S_WRITE_ZEROS	4'b0010
`define S_ZERO		4'b0011
`define S_WRITE2	4'b0100
`define S_WRITE3	4'b0101

module rpn(KEY, SW, LEDR, HEX0, HEX1, HEX2, HEX3, HEX4, HEX5, CLOCK_50);
	input CLOCK_50;
	input [3:0] KEY;
	input [9:0] SW;
	output [9:0] LEDR;
	output [6:0] HEX0, HEX1, HEX2, HEX3, HEX4, HEX5;
	wire [7:0] data_IN, data_OUT, SP, into_SP_reg, output_line, memory_out;
	reg write_dummy, tri_enable, write_SP, write_memory;
	reg [3:0] current_state;
	
	reg_load_enable #(8) STACK_POINTER (CLOCK_50, into_SP_reg, write_SP, SP);
	reg_load_enable #(8) DUMMY_REGISTER (CLOCK_50, data_IN, write_dummy, output_line);
	RAM STACK (CLOCK_50, SP, SP, write_memory, output_line, memory_out); 

	assign data_IN = tri_enable ? SW[7:0] : 8'b0;	
	assign into_SP_reg = tri_enable ? (1'b1 + SP) : 8'b00000000;

	assign LEDR[7:0] = output_line;
	assign LEDR[8] = 1'b0;
	assign LEDR[9] = 1'b0;
	assign HEX0[6:0] = `ZERO;
	assign HEX1[6:0] = `ZERO;
	assign HEX2[6:0] = `ZERO;
	assign HEX3[6:0] = `ZERO;
	assign HEX4[6:0] = `ZERO;
	assign HEX5[6:0] = `ZERO;

	always @(posedge CLOCK_50) begin
		if (~KEY[1]) begin
			current_state = `S_ZERO;
		end else begin
			casex ({current_state, ~KEY[0]})
				{`S_ZERO, 1'bx}: 	current_state = `S_WRITE_ZEROS;
				{`S_WRITE_ZEROS, 1'bx}: current_state = `S_WAIT;
				{`S_WAIT, 1'b0}: 	current_state = `S_WAIT;
				{`S_WAIT, 1'b1}: 	current_state = `S_WRITE1;
				{`S_WRITE1, 1'bx}: 	current_state = `S_WRITE2;
				{`S_WRITE2, 1'bx}: 	current_state = `S_WRITE3;
				{`S_WRITE3, 1'bx}: 	current_state = `S_WAIT;
			endcase

			case (current_state)
				`S_ZERO: 	{write_dummy, write_SP, write_memory, tri_enable} = {1'b0, 1'b0, 1'b0, 1'b0};
				`S_WRITE_ZEROS: {write_dummy, write_SP, write_memory, tri_enable} = {1'b1, 1'b1, 1'b0, 1'b0};
				`S_WAIT: 	{write_dummy, write_SP, write_memory, tri_enable} = {1'b0, 1'b0, 1'b0, 1'b0};
				`S_WRITE1: 	{write_dummy, write_SP, write_memory, tri_enable} = {1'b1, 1'b0, 1'b0, 1'b1};
				`S_WRITE2: 	{write_dummy, write_SP, write_memory, tri_enable} = {1'b0, 1'b0, 1'b1, 1'b1};
				`S_WRITE3:	{write_dummy, write_SP, write_memory, tri_enable} = {1'b0, 1'b1, 1'b0, 1'b1};	
			endcase	
		end
	end
endmodule

rpn_tb.v
module rpn_tb;
	reg CLOCK_50;
	reg [3:0] KEY;
	reg [9:0] SW;
	wire [9:0] LEDR;
	wire [6:0] HEX0, HEX1, HEX2, HEX3, HEX4, HEX5;
	reg [7:0] data_IN, data_OUT;
	reg error;

	rpn DUT(KEY, SW, LEDR, HEX0, HEX1, HEX2, HEX3, HEX4, HEX5, CLOCK_50);
		
	initial forever begin
		CLOCK_50 = 0; #5;
		CLOCK_50 = 1; #5;
	end

	initial begin
		error = 0;
		
		KEY[0] = 1; // set enter button LOW

		KEY[1] = 1'b0; // assert reset
		#10; // wait for rising edge of clock
		KEY[1] = 1'b1; // deassert reset
		

		// set input value on the switches 
		SW[0] = 1'b1;
    		SW[1] = 1'b0;
    		SW[2] = 1'b0;
    		SW[3] = 1'b1;
    		SW[4] = 1'b0;
    		SW[5] = 1'b1;
    		SW[6] = 1'b0;
    		SW[7] = 1'b1;
    		SW[8] = 1'b0;
    		SW[9] = 1'b0;
		
		// wait a while
			
		#100;
		KEY[0] = 0;
		#10;
		KEY[0] = 1;

		#50;

		

		// set input value on the switches 
		SW[0] = 1'b1;
    		SW[1] = 1'b0;
    		SW[2] = 1'b0;
    		SW[3] = 1'b1;
    		SW[4] = 1'b0;
    		SW[5] = 1'b1;
    		SW[6] = 1'b0;
    		SW[7] = 1'b1;
    		SW[8] = 1'b0;
    		SW[9] = 1'b0;

		
		#40;
		KEY[0] = 0;
		#10;
		KEY[0] = 1;
		#40;

		KEY[1] = 0;
		#10;
		KEY[1] = 1;	
		#50;




		if (~error) $display("Calculator probably works.");
		$stop;
	end
endmodule

rpn.vcd
$date
	Tue May 31 21:34:53 2022
$end
$version
	Icarus Verilog
$end
$timescale
	1s
$end
$scope module rpn_tb $end
$var wire 7 ! HEX0 [6:0] $end
$var wire 7 " HEX1 [6:0] $end
$var wire 7 # HEX2 [6:0] $end
$var wire 7 $ HEX3 [6:0] $end
$var wire 7 % HEX4 [6:0] $end
$var wire 7 & HEX5 [6:0] $end
$var wire 10 ' LEDR [9:0] $end
$var reg 1 ( CLOCK_50 $end
$var reg 4 ) KEY [3:0] $end
$var reg 10 * SW [9:0] $end
$var reg 1 + error $end
$scope module DUT $end
$var wire 1 ( CLOCK_50 $end
$var wire 7 , HEX0 [6:0] $end
$var wire 7 - HEX1 [6:0] $end
$var wire 7 . HEX2 [6:0] $end
$var wire 7 / HEX3 [6:0] $end
$var wire 7 0 HEX4 [6:0] $end
$var wire 7 1 HEX5 [6:0] $end
$var wire 4 2 KEY [3:0] $end
$var wire 10 3 SW [9:0] $end
$var wire 8 4 output_line [7:0] $end
$var wire 8 5 memory_out [7:0] $end
$var wire 8 6 into_SP_reg [7:0] $end
$var wire 8 7 data_IN [7:0] $end
$var wire 8 8 SP [7:0] $end
$var wire 10 9 LEDR [9:0] $end
$var reg 4 : current_state [3:0] $end
$var reg 1 ; tri_enable $end
$var reg 1 < write_SP $end
$var reg 1 = write_dummy $end
$var reg 1 > write_memory $end
$scope module DUMMY_REGISTER $end
$var wire 1 ( clk $end
$var wire 1 = enable $end
$var wire 8 ? in [7:0] $end
$var wire 8 @ out [7:0] $end
$var wire 8 A mux_into_reg [7:0] $end
$scope module DFF0 $end
$var wire 1 ( clk $end
$var wire 8 B in [7:0] $end
$var reg 8 C out [7:0] $end
$upscope $end
$scope module MUX0 $end
$var wire 8 D a0 [7:0] $end
$var wire 8 E a1 [7:0] $end
$var wire 1 = s $end
$var reg 8 F out [7:0] $end
$upscope $end
$upscope $end
$scope module STACK $end
$var wire 1 ( clk $end
$var wire 8 G din [7:0] $end
$var wire 1 > write $end
$var wire 8 H write_address [7:0] $end
$var wire 8 I read_address [7:0] $end
$var reg 8 J dout [7:0] $end
$upscope $end
$scope module STACK_POINTER $end
$var wire 1 ( clk $end
$var wire 1 < enable $end
$var wire 8 K in [7:0] $end
$var wire 8 L out [7:0] $end
$var wire 8 M mux_into_reg [7:0] $end
$scope module DFF0 $end
$var wire 1 ( clk $end
$var wire 8 N in [7:0] $end
$var reg 8 O out [7:0] $end
$upscope $end
$scope module MUX0 $end
$var wire 8 P a0 [7:0] $end
$var wire 8 Q a1 [7:0] $end
$var wire 1 < s $end
$var reg 8 R out [7:0] $end
$upscope $end
$upscope $end
$upscope $end
$upscope $end
$enddefinitions $end
#0
$dumpvars
bx R
bx Q
bx P
bx O
bx N
bx M
bx L
bx K
bx J
bx I
bx H
bx G
bx F
bx0x0xxx0 E
bx D
bx C
bx B
bx A
bx @
bx0x0xxx0 ?
x>
x=
x<
x;
bx :
b0xxxxxxxx 9
bx 8
bx0x0xxx0 7
bx 6
bx 5
bx 4
b10101110 3
bx01 2
b1000000 1
b1000000 0
b1000000 /
b1000000 .
b1000000 -
b1000000 ,
0+
b10101110 *
bx01 )
0(
b0xxxxxxxx '
b1000000 &
b1000000 %
b1000000 $
b1000000 #
b1000000 "
b1000000 !
$end
#5
b11 :
1(
#10
0(
bx11 )
bx11 2
#15
b0 A
b0 B
b0 F
b0 M
b0 N
b0 R
b0 7
b0 ?
b0 E
b0 6
b0 K
b0 Q
1=
1<
0>
0;
b10 :
1(
#20
0(
#25
b0 8
b0 H
b0 I
b0 L
b0 O
b0 P
b0 '
b0 9
b0 4
b0 @
b0 C
b0 D
b0 G
0=
0<
b0 :
1(
#30
0(
#35
1(
#40
0(
#45
1(
#50
0(
bx10 )
bx10 2
#55
b10101110 A
b10101110 B
b10101110 F
b10101110 7
b10101110 ?
b10101110 E
b1 6
b1 K
b1 Q
1=
1;
b1 :
1(
#60
0(
bx11 )
bx11 2
#65
b10101110 '
b10101110 9
b10101110 4
b10101110 @
b10101110 C
b10101110 D
b10101110 G
0=
1>
b100 :
1(
#70
0(
#75
b0 5
b0 J
b1 M
b1 N
b1 R
1<
0>
b101 :
1(
#80
0(
#85
b10101110 5
b10101110 J
b0 7
b0 ?
b0 E
b0 6
b0 K
b0 Q
b1 8
b1 H
b1 I
b1 L
b1 O
b1 P
0<
0;
b0 :
1(
#90
0(
#95
bx 5
bx J
1(
#100
0(
b10000011 *
b10000011 3
#105
1(
#110
0(
#115
1(
#120
0(
#125
1(
#130
0(
#135
1(
#140
0(
bx10 )
bx10 2
#145
b10000011 A
b10000011 B
b10000011 F
b10000011 7
b10000011 ?
b10000011 E
b10 6
b10 K
b10 Q
1=
1;
b1 :
1(
#150
0(
bx11 )
bx11 2
#155
0=
1>
b100 :
b10000011 '
b10000011 9
b10000011 4
b10000011 @
b10000011 C
b10000011 D
b10000011 G
1(
#160
0(
#165
b10 M
b10 N
b10 R
1<
0>
b101 :
1(
#170
0(
#175
b0 7
b0 ?
b0 E
b0 6
b0 K
b0 Q
0<
0;
b0 :
b10 8
b10 H
b10 I
b10 L
b10 O
b10 P
1(
#180
0(
#185
1(
#190
0(
bx01 )
bx01 2
#195
b11 :
1(
#200
0(
bx11 )
bx11 2
#205
b0 A
b0 B
b0 F
b0 M
b0 N
b0 R
1=
1<
b10 :
1(
#210
0(
#215
b10101110 5
b10101110 J
0=
0<
b0 :
b0 '
b0 9
b0 4
b0 @
b0 C
b0 D
b0 G
b0 8
b0 H
b0 I
b0 L
b0 O
b0 P
1(
#220
0(
#225
1(
#230
0(
#235
1(
#240
0(
#245
1(
#250
0(
bx10 )
bx10 2
#255
b10000011 A
b10000011 B
b10000011 F
b10000011 7
b10000011 ?
b10000011 E
b1 6
b1 K
b1 Q
1=
1;
b1 :
1(
#260
0(
bx11 )
bx11 2
#265
b10000011 '
b10000011 9
b10000011 4
b10000011 @
b10000011 C
b10000011 D
b10000011 G
0=
1>
b100 :
1(
#270
0(
#275
b0 5
b0 J
b1 M
b1 N
b1 R
1<
0>
b101 :
1(
#280
0(
#285
b10000011 5
b10000011 J
b0 7
b0 ?
b0 E
b0 6
b0 K
b0 Q
b1 8
b1 H
b1 I
b1 L
b1 O
b1 P
0<
0;
b0 :
1(
#290
0(
#295
bx 5
bx J
1(
#300
0(
#305
1(
#310
0(
#315
1(
#320
0(
#325
1(
#330
0(
#335
1(
#340
0(
#345
1(
#350
0(
#355
1(
#360
0(
#365
1(
#370
0(
#375
1(
#380
0(
#385
1(
#390
0(
#395
1(
#400
0(
#405
1(
#410
0(
#415
1(
#420
0(
#425
1(
#430
0(
#435
1(
#440
0(
#445
1(
#450
0(
bx10 )
bx10 2
#455
b10000011 7
b10000011 ?
b10000011 E
b10 6
b10 K
b10 Q
1=
1;
b1 :
1(
#460
0(
bx11 )
bx11 2
#465
0=
1>
b100 :
1(
#470
0(
#475
b10000011 5
b10000011 J
b10 M
b10 N
b10 R
1<
0>
b101 :
1(
#480
0(
#485
b0 7
b0 ?
b0 E
b0 6
b0 K
b0 Q
b10 8
b10 H
b10 I
b10 L
b10 O
b10 P
0<
0;
b0 :
1(
#490
0(
#495
bx 5
bx J
1(
#500
0(
#505
1(
#510
0(
#515
1(
#520
0(
#525
1(
#530
0(
#535
1(
#540
0(
bx10 )
bx10 2
#545
b10000011 7
b10000011 ?
b10000011 E
b11 6
b11 K
b11 Q
1=
1;
b1 :
1(
#550
0(
bx11 )
bx11 2
#555
0=
1>
b100 :
1(
#560
0(
#565
b11 M
b11 N
b11 R
1<
0>
b101 :
1(
#570
0(
#575
b0 7
b0 ?
b0 E
b0 6
b0 K
b0 Q
0<
0;
b0 :
b11 8
b11 H
b11 I
b11 L
b11 O
b11 P
1(
#580
0(
#585
1(
#590
0(
#595
1(
#600
0(
#605
1(
#610
0(
#615
1(
#620
0(
#625
1(
#630
0(
bx10 )
bx10 2
#635
b10000011 7
b10000011 ?
b10000011 E
b100 6
b100 K
b100 Q
1=
1;
b1 :
1(
#640
0(
bx11 )
bx11 2
#645
0=
1>
b100 :
1(
#650
0(
#655
b10000011 5
b10000011 J
b100 M
b100 N
b100 R
1<
0>
b101 :
1(
#660
0(
#665
b0 7
b0 ?
b0 E
b0 6
b0 K
b0 Q
b100 8
b100 H
b100 I
b100 L
b100 O
b100 P
0<
0;
b0 :
1(
#670
0(
#675
bx 5
bx J
1(
#680
0(
#685
1(
#690
0(
#695
1(
#700
0(
#705
1(
#710
0(
#715
1(
#720
0(
#725
1(
#730
0(
#735
1(
#740
0(
#745
1(
#750
0(
#755
1(
#760
0(
#765
1(
#770
0(
#775
1(
#780
0(
bx01 )
bx01 2
#785
b11 :
1(
#790
0(
bx11 )
bx11 2
#795
b0 A
b0 B
b0 F
b0 M
b0 N
b0 R
1=
1<
b10 :
1(
#800
0(
#805
b0 8
b0 H
b0 I
b0 L
b0 O
b0 P
b0 '
b0 9
b0 4
b0 @
b0 C
b0 D
b0 G
0=
0<
b0 :
1(
#810
0(
#815
b10000011 5
b10000011 J
1(
#820
0(
#825
1(
#830
0(
#835
1(
#840
0(
#845
1(
#850
0(
#855
1(
#860
0(
#865
1(
#870
0(
#875
1(
#880
0(
#885
1(
#890
0(
b11111111 *
b11111111 3
#895
1(
#900
0(
#905
1(
#910
0(
#915
1(
#920
0(
#925
1(
#930
0(
bx10 )
bx10 2
#935
b11111111 A
b11111111 B
b11111111 F
b11111111 7
b11111111 ?
b11111111 E
b1 6
b1 K
b1 Q
1=
1;
b1 :
1(
#940
0(
bx11 )
bx11 2
#945
b11111111 '
b11111111 9
b11111111 4
b11111111 @
b11111111 C
b11111111 D
b11111111 G
0=
1>
b100 :
1(
#950
0(
#955
b0 5
b0 J
b1 M
b1 N
b1 R
1<
0>
b101 :
1(
#960
0(
#965
b11111111 5
b11111111 J
b0 7
b0 ?
b0 E
b0 6
b0 K
b0 Q
b1 8
b1 H
b1 I
b1 L
b1 O
b1 P
0<
0;
b0 :
1(
#970
0(
#975
b10000011 5
b10000011 J
1(
